LICENSE
MANIFEST.in
README.md
setup.py
nysbc/__init__.py
nysbc/bibtex.py
nysbc/protocols.conf
nysbc/salk_logo.jpg
nysbc/viewers.py
nysbc/protocols/__init__.py
nysbc/protocols/protocol_3dfsc.py
nysbc/tests/__init__.py
nysbc/tests/test_protocols_nysbc.py
scipion_em_nysbc.egg-info/PKG-INFO
scipion_em_nysbc.egg-info/SOURCES.txt
scipion_em_nysbc.egg-info/dependency_links.txt
scipion_em_nysbc.egg-info/top_level.txt