Metadata-Version: 1.1
Name: scipion-em-nysbc
Version: 1.0.2
Summary: Plugin to use NYSBC programs within the Scipion framework
Home-page: https://github.com/scipion-em/scipion-em-nysbc
Author: Grigory Sharov
Author-email: sharov.grigory@gmail.com
License: UNKNOWN
Keywords: scipion electron-microscopy cryo-em structural-biology image-processing scipion-2.0
Platform: UNKNOWN
Classifier: Development Status :: 4 - Beta
Classifier: License :: OSI Approved :: GNU General Public License v3 (GPLv3)
Classifier: Programming Language :: Python :: 2.7
